backend_common/__init__.py
backend_common/auth/__init__.py
backend_common/auth/dependencies.py
backend_common/auth/manager.py
backend_common/config/__init__.py
backend_common/config/base.py
backend_common/config/service.py
backend_common/database/__init__.py
backend_common/database/manager.py
backend_common/exceptions/__init__.py
backend_common/exceptions/base.py
backend_common/exceptions/business.py
backend_common/exceptions/handlers.py
backend_common/exceptions/http_client.py
backend_common/http_client/__init__.py
backend_common/http_client/client.py
backend_common/http_client/health.py
backend_common/middleware/__init__.py
backend_common/middleware/auth.py
backend_common/middleware/correlation.py
backend_common/middleware/logging.py
backend_common/models/__init__.py
backend_common/models/base.py
backend_common/models/health.py
backend_common/models/pagination.py
backend_common/utils/__init__.py
backend_common/utils/time.py
backend_common/utils/validation.py
backend_common_kato-0.0.6.dist-info/METADATA
backend_common_kato-0.0.6.dist-info/WHEEL
backend_common_kato-0.0.6.dist-info/licenses/LICENSE
backend_common_kato-0.0.6.dist-info/RECORD
