Metadata-Version: 2.4
Name: backend_common_kato
Version: 0.0.6
Summary: Shared common utilities for Python backend services
Project-URL: Homepage, https://github.com/katoo2706/backend-common
Project-URL: Repository, https://github.com/katoo2706/backend-common.git
Project-URL: Issues, https://github.com/Katoo2706/backend-common/issues
Author-email: Kato <katoo2706@gmail.com>
License-File: LICENSE
Classifier: Development Status :: 3 - Alpha
Classifier: Intended Audience :: Developers
Classifier: License :: OSI Approved :: MIT License
Classifier: Programming Language :: Python :: 3
Classifier: Programming Language :: Python :: 3.12
Requires-Python: >=3.12
Requires-Dist: asyncpg>=0.30.0
Requires-Dist: email-validator>=2.0.0
Requires-Dist: fastapi>=0.100.0
Requires-Dist: httpx>=0.24.0
Requires-Dist: passlib[bcrypt]>=1.7.4
Requires-Dist: pydantic-settings>=2.0.0
Requires-Dist: pydantic>=2.0.0
Requires-Dist: pytest>=8.4.2
Requires-Dist: python-jose[cryptography]>=3.3.0
Requires-Dist: python-multipart>=0.0.6
Requires-Dist: sqlalchemy>=2.0.0
Requires-Dist: structlog>=23.0.0
